README.md
license.txt
setup.cfg
setup.py
src/cfcapi/__init__.py
src/cfcapi/board.py
src/cfcapi/config.py
src/cfcapi.egg-info/PKG-INFO
src/cfcapi.egg-info/SOURCES.txt
src/cfcapi.egg-info/dependency_links.txt
src/cfcapi.egg-info/requires.txt
src/cfcapi.egg-info/top_level.txt