Metadata-Version: 2.1
Name: cfcapi
Version: 1.0.1
Summary: API for the Caonabo Fluidic Controller (CFC)
Home-page: https://github.imec.be/dna-storage/cfcapi
Author: César J. Lockhart de la Rosa
Author-email: lockhart@imec.be
License: MIT
Keywords: fluidic controller,api,caonabo
Platform: UNKNOWN
License-File: license.txt
